{
    "id": "ekstep.analytics.report.get",
    "ver": "1.0",
    "ts": "2023-06-01T08:13:14.890+00:00",
    "params": {
        "resmsgid": "3af0c172-97c9-4d10-875c-9b8a00b39e8e",
        "status": "successful",
        "client_key": null
    },
    "responseCode": "OK",
    "result": {
        "createdOn": 1669378062365,
        "updatedOn": 1669378062365,
        "reportId": "ml_total_unique_users_api_testo_pabitra_new1_one",
        "config": {
            "streamQuery": true,
            "reportConfig": {
                "id": "ml_total_unique_users_api_testo_pabitra_new1_one",
                "mergeConfig": {
                    "postContainer": "odev-dev-diksha-privatereports",
                    "container": "odev-dev-diksha-privatereports",
                    "basePath": "/mount/data/analytics/tmp",
                    "reportPath": "ml_total_unique_users_api_testo_pabitra_new1_one.csv",
                    "rollup": 0
                },
                "labels": {
                    "district_externalId": "district_externalId",
                    "program_id": "program_id",
                    "SUM(unique_users)": "total_content_plays_on_portal",
                    "legend": "Total Unique Users",
                    "solution_id": "solution_id",
                    "total_content_plays_on_portal": "Total Unique Users",
                    "organisation_name": "organisation_name",
                    "organisation_id": "organisation_id",
                    "parent_channel": "parent_channel",
                    "district_name": "district_name",
                    "program_name": "Program name",
                    "state_slug": "state_slug",
                    "solution_name": "Observation name"
                },
                "dateRange": {
                    "staticInterval": "LastDay",
                    "granularity": "all",
                    "intervalSlider": 0
                },
                "metrics": [
                    {
                        "metric": "total_content_plays_on_portal",
                        "label": "total_content_plays_on_portal",
                        "druidQuery": {
                            "dataSource": "ml-obs-status",
                            "limitSpec": {
                                "type": "default",
                                "limit": 10000,
                                "columns": [
                                    {
                                        "dimension": "SUM(unique_users)",
                                        "direction": "descending"
                                    }
                                ]
                            },
                            "filters": [
                                {
                                    "type": "equals",
                                    "dimension": "status",
                                    "value": "completed"
                                },
                                {
                                    "type": "equals",
                                    "dimension": "private_program",
                                    "value": "false"
                                },
                                {
                                    "type": "equals",
                                    "dimension": "solution_type",
                                    "value": "observation_with_rubric"
                                }
                            ],
                            "granularity": "all",
                            "dimensions": [
                                {
                                    "fieldName": "parent_channel",
                                    "aliasName": "parent_channel"
                                },
                                {
                                    "fieldName": "district_name",
                                    "aliasName": "district_name"
                                },
                                {
                                    "fieldName": "program_name",
                                    "aliasName": "Program name"
                                },
                                {
                                    "fieldName": "solution_name",
                                    "aliasName": "Observation name"
                                },
                                {
                                    "fieldName": "organisation_name",
                                    "aliasName": "organisation_name"
                                },
                                {
                                    "fieldName": "solution_id",
                                    "aliasName": "solution_id"
                                },
                                {
                                    "fieldName": "district_externalId",
                                    "aliasName": "district_externalId"
                                },
                                {
                                    "fieldName": "organisation_id",
                                    "aliasName": "organisation_id"
                                },
                                {
                                    "fieldName": "program_id",
                                    "aliasName": "program_id"
                                }
                            ],
                            "aggregations": [
                                {
                                    "fieldName": "unique_users",
                                    "type": "longSum",
                                    "name": "total_content_plays_on_portal"
                                }
                            ],
                            "postAggregations": [],
                            "queryType": "groupBy"
                        }
                    }
                ],
                "output": [
                    {
                        "type": "csv",
                        "metrics": [
                            "total_content_plays_on_portal"
                        ],
                        "dims": [
                            "date",
                            "solution_id"
                        ],
                        "fileParameters": [
                            "id",
                            "dims"
                        ]
                    }
                ],
                "queryType": "groupBy"
            },
            "container": "odev-dev-diksha-privatereports",
            "store": "oci",
            "key": "hawk-eye/"
        },
        "requestedBy": "423647fd-701a-4e74-b0cf-a959c49459ab",
        "reportDescription": "Total no of active unique users",
        "submittedOn": 1669378062365,
        "status": "ACTIVE",
        "status_msg": "REPORT SUCCESSFULLY ACTIVATED",
        "reportSchedule": "DAILY"
    }
}